pyYAHTS/__init__.py
pyYAHTS/datatable_footer.j2
pyYAHTS/datatable_header.j2
pyYAHTS/iosxe class.j2
pyYAHTS/iosxe csv.j2
pyYAHTS/iosxe flowchart.j2
pyYAHTS/iosxe graph_csv.j2
pyYAHTS/iosxe html.j2
pyYAHTS/iosxe md.j2
pyYAHTS/iosxe mindmap.j2
pyYAHTS/iosxe mp3.j2
pyYAHTS/iosxe pie.j2
pyYAHTS/iosxe relationship.j2
pyYAHTS/iosxe state.j2
pyYAHTS/nxos class.j2
pyYAHTS/nxos csv.j2
pyYAHTS/nxos flowchart.j2
pyYAHTS/nxos graph_csv.j2
pyYAHTS/nxos html.j2
pyYAHTS/nxos md.j2
pyYAHTS/nxos mindmap.j2
pyYAHTS/nxos mp3.j2
pyYAHTS/nxos pie.j2
pyYAHTS/nxos relationship.j2
pyYAHTS/nxos state.j2
pyYAHTS/pyYAHTS.py
pyYAHTS/script.py
pyyahts-1.0.50.dist-info/entry_points.txt
pyyahts-1.0.50.dist-info/LICENSE
pyyahts-1.0.50.dist-info/WHEEL
pyyahts-1.0.50.dist-info/METADATA
pyyahts-1.0.50.dist-info/RECORD
