Metadata-Version: 2.1
Name: pyyahts
Version: 1.0.50
Summary: An implementation of Cisco pyATS
Home-page: https://github.com/automateyournetwork/pyYAHTS
Author: John Capobianco
Author-email: ptcapo@gmail.com
Requires-Python: >=3.8,<4.0
Classifier: Programming Language :: Python :: 3
Classifier: Programming Language :: Python :: 3.10
Classifier: Programming Language :: Python :: 3.8
Classifier: Programming Language :: Python :: 3.9
Requires-Dist: fpdf (>=1.7.2,<2.0.0)
Requires-Dist: gTTS (>=2.2.4,<3.0.0)
Requires-Dist: json2table (>=1.1.5,<2.0.0)
Requires-Dist: networkx (>=2.7.1,<3.0.0)
Requires-Dist: pandas (>=1.4.1,<2.0.0)
Requires-Dist: pyats[full] (==22.1)
Requires-Dist: pyvis (>=0.1.9,<0.2.0)
Requires-Dist: rich (>=12.1.0,<13.0.0)
Requires-Dist: rich-click (>=1.2.1,<2.0.0)
Requires-Dist: tabulate (>=0.8.9,<0.9.0)
Project-URL: Repository, https://github.com/automateyournetwork/pyYAHTS
